scripts/bump-version.py
scripts/deploy.sh
tdd_mcp_server/__init__.py
tdd_mcp_server/_version.py
tdd_mcp_server/cli.py
tdd_mcp_server/config.py
tdd_mcp_server/server.py
tdd_mcp_server/tdd-mcp-server.mdc
tdd_mcp_server/tool_runner.py
tdd_mcp_server-0.0.1.dist-info/licenses/LICENSE
tests/__init__.py
tests/test_config.py
tests/test_integration.py
tdd_mcp_server-0.0.1.dist-info/METADATA
tdd_mcp_server-0.0.1.dist-info/WHEEL
tdd_mcp_server-0.0.1.dist-info/entry_points.txt
tdd_mcp_server-0.0.1.dist-info/top_level.txt
tdd_mcp_server-0.0.1.dist-info/RECORD
